lib_collection/__init__.py
lib_collection/node.py
lib_collection/priority_queue/__init__.py
lib_collection/priority_queue/fixed_size_max_priority_queue.py
lib_collection/priority_queue/fixed_size_min_priority_queue.py
lib_collection/priority_queue/max_priority_queue.py
lib_collection/priority_queue/min_priority_queue.py
lib_collection/queue/__init__.py
lib_collection/queue/fixed_capacity_array_queue.py
lib_collection/queue/linked_queue.py
lib_collection/queue/resizing_array_queue.py
lib_collection/queue/simple_linked_queue.py
lib_collection/search/__init__.py
lib_collection/search/binary_search_kvstore.py
lib_collection/search/bst_kvstore.py
lib_collection/search/linear_probing_kvstore.py
lib_collection/search/separate_chaining_hash_kvstore.py
lib_collection/search/sequential_search_kvstore.py
lib_collection/sort/__init__.py
lib_collection/sort/bubble_sort.py
lib_collection/sort/heap_sort.py
lib_collection/sort/insertion_sort.py
lib_collection/sort/merge_sort.py
lib_collection/sort/quick_bubble_sort.py
lib_collection/sort/quick_selection_sort.py
lib_collection/sort/quick_sort.py
lib_collection/sort/recursive_selection_sort.py
lib_collection/sort/selection_sort.py
lib_collection/sort/shell_sort.py
lib_collection/stack/__init__.py
lib_collection/stack/linked_stack.py
lib_collection/stack/resizing_array_stack.py
lib_collection/tree/__init__.py
lib_collection/tree/list_of_lists_representation.py
lib_collection/union_find/__init__.py
lib_collection/union_find/quick_find_union_find.py
lib_collection/union_find/quick_union_union_find.py
lib_collection/union_find/union_find.py
lib_collection/union_find/weighted_union_find.py
jx_libcollection-0.0.17.dist-info/LICENSE
jx_libcollection-0.0.17.dist-info/METADATA
jx_libcollection-0.0.17.dist-info/WHEEL
jx_libcollection-0.0.17.dist-info/top_level.txt
jx_libcollection-0.0.17.dist-info/RECORD
