Metadata-Version: 2.1
Name: jx-libcollection
Version: 0.0.17
Summary: Jiao's collection libs
Home-page: https://github.com/caser789/libcollection
Author: jiao.xue
Author-email: jiao.xuejiao@gmail.com
License: UNKNOWN
Platform: UNKNOWN
Classifier: Programming Language :: Python :: 2
Classifier: License :: OSI Approved :: MIT License
Classifier: Operating System :: OS Independent
